[{"__symbolic":"module","version":3,"metadata":{"WheelSelectorOptions":{"__symbolic":"interface"},"WheelSelectorData":{"__symbolic":"interface"},"WheelSelector":{"__symbolic":"class","extends":{"__symbolic":"reference","module":"@ionic-native/core","name":"IonicNativePlugin"},"decorators":[{"__symbolic":"call","expression":{"__symbolic":"reference","module":"@ionic-native/core","name":"Plugin"},"arguments":[{"pluginName":"WheelSelector","plugin":"cordova-wheel-selector-plugin","pluginRef":"SelectorCordovaPlugin","repo":"","platforms":[]}]},{"__symbolic":"call","expression":{"__symbolic":"reference","module":"@angular/core","name":"Injectable"}}],"members":{"show":[{"__symbolic":"method","decorators":[{"__symbolic":"call","expression":{"__symbolic":"reference","module":"@ionic-native/core","name":"Cordova"}}]}]}}}},{"__symbolic":"module","version":1,"metadata":{"WheelSelectorOptions":{"__symbolic":"interface"},"WheelSelectorData":{"__symbolic":"interface"},"WheelSelector":{"__symbolic":"class","extends":{"__symbolic":"reference","module":"@ionic-native/core","name":"IonicNativePlugin"},"decorators":[{"__symbolic":"call","expression":{"__symbolic":"reference","module":"@ionic-native/core","name":"Plugin"},"arguments":[{"pluginName":"WheelSelector","plugin":"cordova-wheel-selector-plugin","pluginRef":"SelectorCordovaPlugin","repo":"","platforms":[]}]},{"__symbolic":"call","expression":{"__symbolic":"reference","module":"@angular/core","name":"Injectable"}}],"members":{"show":[{"__symbolic":"method","decorators":[{"__symbolic":"call","expression":{"__symbolic":"reference","module":"@ionic-native/core","name":"Cordova"}}]}]}}}}]